rimopy/__init__.py
rimopy/_version.py
rimopy/coefficients.py
rimopy/correction_factor.py
rimopy/eli.py
rimopy/elref.py
rimopy/esi.py
rimopy/geometry.py
rimopy/spice_iface.py
rimopy/types.py
rimopy/data/README.txt
rimopy/data/coefficients.csv
rimopy/data/wehrli_asc.csv
rimopy/data/wehrli_filtered.csv
rimopy/data/wehrli_gaussian.csv
rimopy/data/wehrli_original.csv
rimopy/tests/__init__.py
rimopy/tests/test_eli_aemet.py
rimopy/tests/test_eli_caelis.py
rimopy/tests/assets/caelis_sample.csv
rimopy/tests/kernels/de421.bsp
rimopy/tests/kernels/earth_070425_370426_predict.bpc
rimopy/tests/kernels/earth_assoc_itrf93.tf
rimopy/tests/kernels/earth_latest_high_prec.bpc
rimopy/tests/kernels/moon_080317.tf
rimopy/tests/kernels/moon_pa_de421_1900-2050.bpc
rimopy/tests/kernels/naif0011.tls
rimopy/tests/kernels/pck00010.tpc
rimopy-0.4.2.dist-info/licenses/LICENSE
rimopy-0.4.2.dist-info/METADATA
rimopy-0.4.2.dist-info/WHEEL
rimopy-0.4.2.dist-info/top_level.txt
rimopy-0.4.2.dist-info/RECORD
