Metadata-Version: 2.4
Name: rimopy
Version: 0.4.2
Summary: ROLO Implementation for Moon photometry Observation (RIMO), in Python
Author-email: Javier Gatón Herguedas <gaton@goa.uva.es>
Maintainer-email: Javier Gatón Herguedas <gaton@goa.uva.es>
License-Expression: LGPL-3.0-only
Project-URL: Homepage, https://github.com/GOA-UVa/rimopy
Project-URL: Repository, https://github.com/GOA-UVa/rimopy.git
Project-URL: Issues, https://github.com/GOA-UVa/rimopy/issues
Classifier: Development Status :: 3 - Alpha
Classifier: Intended Audience :: Science/Research
Classifier: Natural Language :: English
Classifier: Operating System :: OS Independent
Classifier: Programming Language :: Python :: 3
Classifier: Programming Language :: Python :: 3.8
Classifier: Programming Language :: Python :: 3.9
Classifier: Programming Language :: Python :: 3.10
Classifier: Programming Language :: Python :: 3.11
Classifier: Programming Language :: Python :: 3.12
Classifier: Programming Language :: Python :: 3.13
Classifier: Programming Language :: Python :: 3.14
Classifier: Topic :: Scientific/Engineering :: Astronomy
Classifier: Topic :: Scientific/Engineering :: Atmospheric Science
Requires-Python: >=3.8
License-File: LICENSE
Requires-Dist: numpy>=1.22.0
Requires-Dist: spicedmoon>=1.0.13
Dynamic: license-file
